{
  "generated_at": "2026-01-14T12:48:28.629201+00:00",
  "window_hours": 24,
  "totals": {
    "positive": 1265,
    "neutral": 509,
    "negative": 1652
  },
  "by_publication": [
    {
      "source": "Independent",
      "positive": 233,
      "neutral": 109,
      "negative": 334,
      "count": 676,
      "region": "North America"
    },
    {
      "source": "The Hindu",
      "positive": 118,
      "neutral": 82,
      "negative": 97,
      "count": 297,
      "region": "Asia-Pacific"
    },
    {
      "source": "Bloomberg",
      "positive": 111,
      "neutral": 27,
      "negative": 76,
      "count": 214,
      "region": "North America"
    },
    {
      "source": "Fox News",
      "positive": 44,
      "neutral": 15,
      "negative": 133,
      "count": 192,
      "region": "North America"
    },
    {
      "source": "Times of India",
      "positive": 71,
      "neutral": 27,
      "negative": 92,
      "count": 190,
      "region": "Asia-Pacific"
    },
    {
      "source": "The Guardian",
      "positive": 45,
      "neutral": 4,
      "negative": 90,
      "count": 139,
      "region": "Europe"
    },
    {
      "source": "Channel News Asia",
      "positive": 42,
      "neutral": 48,
      "negative": 48,
      "count": 138,
      "region": "Global"
    },
    {
      "source": "CBS News",
      "positive": 54,
      "neutral": 18,
      "negative": 64,
      "count": 136,
      "region": "North America"
    },
    {
      "source": "Australian Broadcasting Corporation",
      "positive": 36,
      "neutral": 9,
      "negative": 84,
      "count": 129,
      "region": "Asia-Pacific"
    },
    {
      "source": "BBC News",
      "positive": 30,
      "neutral": 26,
      "negative": 45,
      "count": 101,
      "region": "Asia-Pacific"
    },
    {
      "source": "South China Morning Post",
      "positive": 44,
      "neutral": 1,
      "negative": 51,
      "count": 96,
      "region": "North America"
    },
    {
      "source": "France 24",
      "positive": 24,
      "neutral": 4,
      "negative": 44,
      "count": 72,
      "region": "Europe"
    },
    {
      "source": "Al Jazeera English",
      "positive": 21,
      "neutral": 5,
      "negative": 44,
      "count": 70,
      "region": "North America"
    },
    {
      "source": "Euronews",
      "positive": 25,
      "neutral": 4,
      "negative": 36,
      "count": 65,
      "region": "Europe"
    },
    {
      "source": "CNBC",
      "positive": 23,
      "neutral": 20,
      "negative": 17,
      "count": 60,
      "region": "North America"
    },
    {
      "source": "ESPN",
      "positive": 37,
      "neutral": 10,
      "negative": 13,
      "count": 60,
      "region": "Europe"
    },
    {
      "source": "NBC News",
      "positive": 9,
      "neutral": 12,
      "negative": 38,
      "count": 59,
      "region": "North America"
    },
    {
      "source": "BBC Sport",
      "positive": 30,
      "neutral": 8,
      "negative": 19,
      "count": 57,
      "region": "Asia-Pacific"
    },
    {
      "source": "AllAfrica",
      "positive": 23,
      "neutral": 5,
      "negative": 23,
      "count": 51,
      "region": "Africa"
    },
    {
      "source": "Times of Israel",
      "positive": 6,
      "neutral": 1,
      "negative": 40,
      "count": 47,
      "region": "Middle East"
    },
    {
      "source": "Mashable",
      "positive": 32,
      "neutral": 8,
      "negative": 7,
      "count": 47,
      "region": "North America"
    },
    {
      "source": "MarketWatch",
      "positive": 27,
      "neutral": 7,
      "negative": 9,
      "count": 43,
      "region": "Global"
    },
    {
      "source": "Sky Sports",
      "positive": 25,
      "neutral": 8,
      "negative": 10,
      "count": 43,
      "region": "Asia-Pacific"
    },
    {
      "source": "Irish Times",
      "positive": 16,
      "neutral": 6,
      "negative": 17,
      "count": 39,
      "region": "North America"
    },
    {
      "source": "New York Times",
      "positive": 10,
      "neutral": 4,
      "negative": 23,
      "count": 37,
      "region": "North America"
    },
    {
      "source": "Financial Times",
      "positive": 20,
      "neutral": 1,
      "negative": 16,
      "count": 37,
      "region": "Middle East"
    },
    {
      "source": "Straits Times",
      "positive": 8,
      "neutral": 11,
      "negative": 16,
      "count": 35,
      "region": "Global"
    },
    {
      "source": "Deutsche Welle",
      "positive": 3,
      "neutral": 1,
      "negative": 28,
      "count": 32,
      "region": "North America"
    },
    {
      "source": "ABC News",
      "positive": 10,
      "neutral": 3,
      "negative": 18,
      "count": 31,
      "region": "North America"
    },
    {
      "source": "RT News",
      "positive": 7,
      "neutral": 6,
      "negative": 16,
      "count": 29,
      "region": "North America"
    },
    {
      "source": "The Verge",
      "positive": 12,
      "neutral": 4,
      "negative": 11,
      "count": 27,
      "region": "North America"
    },
    {
      "source": "Middle East Eye",
      "positive": 8,
      "neutral": 0,
      "negative": 18,
      "count": 26,
      "region": "Middle East"
    },
    {
      "source": "Sky News",
      "positive": 2,
      "neutral": 1,
      "negative": 23,
      "count": 26,
      "region": "Middle East"
    },
    {
      "source": "NPR",
      "positive": 7,
      "neutral": 4,
      "negative": 13,
      "count": 24,
      "region": "North America"
    },
    {
      "source": "Engadget",
      "positive": 15,
      "neutral": 0,
      "negative": 6,
      "count": 21,
      "region": "North America"
    },
    {
      "source": "Wired",
      "positive": 14,
      "neutral": 2,
      "negative": 3,
      "count": 19,
      "region": "Global"
    },
    {
      "source": "Daily News Egypt",
      "positive": 10,
      "neutral": 2,
      "negative": 4,
      "count": 16,
      "region": "Middle East"
    },
    {
      "source": "Washington Post",
      "positive": 3,
      "neutral": 1,
      "negative": 11,
      "count": 15,
      "region": "Asia-Pacific"
    },
    {
      "source": "Ars Technica",
      "positive": 4,
      "neutral": 4,
      "negative": 7,
      "count": 15,
      "region": "Global"
    },
    {
      "source": "Telegraph",
      "positive": 4,
      "neutral": 1,
      "negative": 5,
      "count": 10,
      "region": "Asia-Pacific"
    },
    {
      "source": "Buenos Aires Herald",
      "positive": 2,
      "neutral": 0,
      "negative": 3,
      "count": 5,
      "region": "South America"
    }
  ],
  "by_region": [
    {
      "region": "North America",
      "positive": 497,
      "neutral": 188,
      "negative": 703,
      "count": 1388
    },
    {
      "region": "Asia-Pacific",
      "positive": 268,
      "neutral": 121,
      "negative": 327,
      "count": 716
    },
    {
      "region": "Europe",
      "positive": 283,
      "neutral": 118,
      "negative": 285,
      "count": 686
    },
    {
      "region": "Middle East",
      "positive": 57,
      "neutral": 14,
      "negative": 252,
      "count": 323
    },
    {
      "region": "Global",
      "positive": 129,
      "neutral": 55,
      "negative": 59,
      "count": 243
    },
    {
      "region": "Africa",
      "positive": 24,
      "neutral": 7,
      "negative": 17,
      "count": 48
    },
    {
      "region": "South America",
      "positive": 7,
      "neutral": 6,
      "negative": 9,
      "count": 22
    }
  ],
  "by_topic": [
    {
      "topic": "Politics",
      "positive": 283,
      "neutral": 105,
      "negative": 417,
      "count": 805
    },
    {
      "topic": "Tech",
      "positive": 293,
      "neutral": 104,
      "negative": 393,
      "count": 790
    },
    {
      "topic": "Other",
      "positive": 182,
      "neutral": 127,
      "negative": 229,
      "count": 538
    },
    {
      "topic": "World",
      "positive": 114,
      "neutral": 32,
      "negative": 217,
      "count": 363
    },
    {
      "topic": "Business",
      "positive": 143,
      "neutral": 41,
      "negative": 88,
      "count": 272
    },
    {
      "topic": "Sports",
      "positive": 111,
      "neutral": 43,
      "negative": 95,
      "count": 249
    },
    {
      "topic": "Entertainment",
      "positive": 42,
      "neutral": 17,
      "negative": 59,
      "count": 118
    },
    {
      "topic": "Health",
      "positive": 32,
      "neutral": 7,
      "negative": 71,
      "count": 110
    },
    {
      "topic": "Regional",
      "positive": 20,
      "neutral": 9,
      "negative": 43,
      "count": 72
    },
    {
      "topic": "Local",
      "positive": 19,
      "neutral": 13,
      "negative": 24,
      "count": 56
    },
    {
      "topic": "Science",
      "positive": 26,
      "neutral": 11,
      "negative": 16,
      "count": 53
    }
  ],
  "sample_headlines": [
    {
      "title": "Allowing shorter-term renewals will likely amplify peak and trough of COE cycles: Jeffrey Siow",
      "url": "https://www.straitstimes.com/singapore/politics/allowing-shorter-term-renewals-will-likely-amplify-peak-and-trough-of-coe-cycles-jeffrey-siow",
      "source": "Straits Times",
      "region": "Global",
      "published": "2026-01-14T20:45:00+08:00",
      "sentiment": "positive"
    },
    {
      "title": "Parliament backs motion to express regret at Pritam Singh\u2019s conduct, deem him unfit as Leader of the Opposition",
      "url": "https://www.channelnewsasia.com/singapore/parliament-pritam-singh-workers-party-motion-leader-opposition-indranee-rajah-5858171",
      "source": "Channel News Asia",
      "region": "Global",
      "published": "2026-01-14T20:44:51+08:00",
      "sentiment": "negative"
    },
    {
      "title": "UK PM Starmer says X moves to comply with UK law over AI deepfakes",
      "url": "https://www.channelnewsasia.com/business/uk-pm-starmer-says-x-moves-comply-uk-law-over-ai-deepfakes-5858801",
      "source": "Channel News Asia",
      "region": "Europe",
      "published": "2026-01-14T20:38:32+08:00",
      "sentiment": "neutral"
    },
    {
      "title": "French speed skater Loubineaud puts progress first as he prepares for Olympic debut",
      "url": "https://www.channelnewsasia.com/sport/french-speed-skater-loubineaud-puts-progress-first-he-prepares-olympic-debut-5858786",
      "source": "Channel News Asia",
      "region": "Global",
      "published": "2026-01-14T20:29:08+08:00",
      "sentiment": "positive"
    },
    {
      "title": "Honeywell announces Quantinuum's plan to file for IPO",
      "url": "https://www.channelnewsasia.com/business/honeywell-announces-quantinuums-plan-file-ipo-5858756",
      "source": "Channel News Asia",
      "region": "Global",
      "published": "2026-01-14T20:22:14+08:00",
      "sentiment": "neutral"
    },
    {
      "title": "Belgian cybersecurity startup Aikido hits unicorn status with new funding round",
      "url": "https://www.channelnewsasia.com/business/belgian-cybersecurity-startup-aikido-hits-unicorn-status-new-funding-round-5858691",
      "source": "Channel News Asia",
      "region": "North America",
      "published": "2026-01-14T20:08:03+08:00",
      "sentiment": "neutral"
    },
    {
      "title": "Government close to finalising low-cost retirement investment scheme details: Tan See Leng",
      "url": "https://www.straitstimes.com/singapore/politics/government-close-to-finalising-low-cost-retirement-investment-scheme-details-tan-see-leng",
      "source": "Straits Times",
      "region": "Global",
      "published": "2026-01-14T20:05:00+08:00",
      "sentiment": "negative"
    },
    {
      "title": "Parliament deems Pritam Singh unsuitable to continue as Leader of the Opposition",
      "url": "https://www.straitstimes.com/singapore/politics/parliament-deems-pritam-singh-unsuitable-to-continue-as-leader-of-the-opposition",
      "source": "Straits Times",
      "region": "Global",
      "published": "2026-01-14T20:03:05+08:00",
      "sentiment": "neutral"
    },
    {
      "title": "Retail traders pile into memory chipmakers as AI boom squeezes supplies, lifts prices",
      "url": "https://www.channelnewsasia.com/business/retail-traders-pile-memory-chipmakers-ai-boom-squeezes-supplies-lifts-prices-5858651",
      "source": "Channel News Asia",
      "region": "Global",
      "published": "2026-01-14T19:57:21+08:00",
      "sentiment": "neutral"
    },
    {
      "title": "CNA Explains: The impeachment bid against Taiwan\u2019s Lai \u2013 and why it\u2019s unlikely to succeed",
      "url": "https://www.channelnewsasia.com/east-asia/taiwan-president-william-lai-impeachment-bid-dpp-kmt-unlikely-succeed-5858436",
      "source": "Channel News Asia",
      "region": "Global",
      "published": "2026-01-14T19:46:00+08:00",
      "sentiment": "positive"
    },
    {
      "title": "Esports, chess and bridge formally recognised as sports after Bill passed in parliament",
      "url": "https://www.channelnewsasia.com/singapore/esports-chess-bridge-sports-bill-passed-parliament-5857686",
      "source": "Channel News Asia",
      "region": "Global",
      "published": "2026-01-14T19:43:00+08:00",
      "sentiment": "positive"
    },
    {
      "title": "Pritam Singh rejects motion against him, says his \u2018conscience remains clear\u2019",
      "url": "https://www.straitstimes.com/singapore/politics/pritam-singh-rejects-motion-against-him-says-his-conscience-remains-clear",
      "source": "Straits Times",
      "region": "Global",
      "published": "2026-01-14T19:42:18+08:00",
      "sentiment": "negative"
    },
    {
      "title": "Rare Himalayan vulture found in Kranji put down after health worsened: Mandai Wildlife Group",
      "url": "https://www.straitstimes.com/singapore/rare-himalayan-vulture-found-in-kranji-put-down-after-health-worsened-mandai-wildlife-group",
      "source": "Straits Times",
      "region": "North America",
      "published": "2026-01-14T19:09:54+08:00",
      "sentiment": "negative"
    },
    {
      "title": "Three taken to hospital after 8-vehicle pile-up on AYE",
      "url": "https://www.straitstimes.com/singapore/three-taken-to-hospital-after-8-vehicle-pile-up-on-aye",
      "source": "Straits Times",
      "region": "Global",
      "published": "2026-01-14T18:48:45+08:00",
      "sentiment": "negative"
    },
    {
      "title": "India's Infosys beats Q3 revenue view; ups annual forecast range",
      "url": "https://www.channelnewsasia.com/business/indias-infosys-beats-q3-revenue-view-ups-annual-forecast-range-5858466",
      "source": "Channel News Asia",
      "region": "Asia-Pacific",
      "published": "2026-01-14T18:46:30+08:00",
      "sentiment": "neutral"
    },
    {
      "title": "China probes largest online travel agency Trip.com over suspected monopoly",
      "url": "https://www.channelnewsasia.com/east-asia/china-probes-tripcom-largest-online-travel-agency-suspected-monopoly-5858301",
      "source": "Channel News Asia",
      "region": "North America",
      "published": "2026-01-14T18:37:00+08:00",
      "sentiment": "negative"
    },
    {
      "title": "3 people taken to hospital after crash involving cars and motorcycles on AYE",
      "url": "https://www.channelnewsasia.com/singapore/accident-aye-crash-motorcyclists-cars-hospital-5858346",
      "source": "Channel News Asia",
      "region": "Global",
      "published": "2026-01-14T18:27:00+08:00",
      "sentiment": "negative"
    },
    {
      "title": "Figure skating-French ice dancer Cizeron accuses former partner of smear campaign",
      "url": "https://www.channelnewsasia.com/sport/figure-skating-french-ice-dancer-cizeron-accuses-former-partner-smear-campaign-5858446",
      "source": "Channel News Asia",
      "region": "North America",
      "published": "2026-01-14T18:26:12+08:00",
      "sentiment": "negative"
    },
    {
      "title": "New workgroup to review training for private-hire car licence after Autobahn saga",
      "url": "https://www.straitstimes.com/singapore/politics/new-workgroup-to-review-training-for-private-hire-car-licence-after-autobahn-saga",
      "source": "Straits Times",
      "region": "Global",
      "published": "2026-01-14T18:25:00+08:00",
      "sentiment": "neutral"
    },
    {
      "title": "Teenager admits to stealing delivery parcels left outside Bishan flats, including S$140 vacuum cleaner",
      "url": "https://www.channelnewsasia.com/singapore/teenager-stole-delivery-parcels-hdb-flats-doorsteps-5858326",
      "source": "Channel News Asia",
      "region": "North America",
      "published": "2026-01-14T18:24:16+08:00",
      "sentiment": "negative"
    },
    {
      "title": "Iran warned regional states of strikes on US bases if attacked, official says",
      "url": "https://www.channelnewsasia.com/world/iran-warn-strikes-us-bases-if-attacked-regional-states-5858366",
      "source": "Channel News Asia",
      "region": "North America",
      "published": "2026-01-14T18:16:50+08:00",
      "sentiment": "negative"
    },
    {
      "title": "Iran warns neighbours it could hit US bases if Washington strikes",
      "url": "https://www.channelnewsasia.com/world/iran-warn-strikes-us-bases-if-attacked-regional-states-5858366",
      "source": "Channel News Asia",
      "region": "North America",
      "published": "2026-01-14T18:16:00+08:00",
      "sentiment": "negative"
    },
    {
      "title": "Over one in four platform workers opted in for higher CPF contributions as at Sept 2025",
      "url": "https://www.straitstimes.com/singapore/politics/over-one-in-four-platform-workers-opted-in-for-higher-cpf-contributions-as-at-sept-2025",
      "source": "Straits Times",
      "region": "Global",
      "published": "2026-01-14T18:15:00+08:00",
      "sentiment": "neutral"
    },
    {
      "title": "Over one in four platform workers opted in to make higher CPF contributions as at Sept 2025",
      "url": "https://www.straitstimes.com/singapore/politics/over-one-in-four-platform-workers-opted-in-for-higher-cpf-contributions-as-at-sept-2025",
      "source": "Straits Times",
      "region": "Global",
      "published": "2026-01-14T18:15:00+08:00",
      "sentiment": "neutral"
    },
    {
      "title": "Centre to release first instalment of \u20b9260 cr to Telangana Gram Panchayats: Union Minister Kishan Reddy",
      "url": "https://www.thehindu.com/news/national/telangana/centre-to-release-first-instalment-of-260-cr-to-telangana-gram-panchayats-union-minister-kishan-reddy/article70509405.ece",
      "source": "The Hindu",
      "region": "Asia-Pacific",
      "published": "2026-01-14T18:04:11+05:30",
      "sentiment": "neutral"
    },
    {
      "title": "Indonesian ride-hailing industry set for shake-up under draft presidential decree, sources say",
      "url": "https://www.channelnewsasia.com/asia/indonesia-ride-hailing-prabowo-subianto-gojek-grab-5857981",
      "source": "Channel News Asia",
      "region": "North America",
      "published": "2026-01-14T17:57:58+08:00",
      "sentiment": "negative"
    },
    {
      "title": "Australia's Hazlewood 'on track' to start T20 World Cup after Ashes absence",
      "url": "https://www.channelnewsasia.com/sport/australias-hazlewood-track-start-t20-world-cup-after-ashes-absence-5858361",
      "source": "Channel News Asia",
      "region": "North America",
      "published": "2026-01-14T17:48:10+08:00",
      "sentiment": "neutral"
    },
    {
      "title": "Two baby capybaras born in Mandai, the first in 10 years",
      "url": "https://www.straitstimes.com/singapore/two-baby-capybaras-born-in-mandai-the-first-in-10-years",
      "source": "Straits Times",
      "region": "North America",
      "published": "2026-01-14T17:43:59+08:00",
      "sentiment": "neutral"
    },
    {
      "title": "'Vital for Golden Dome': Trump's new reason for Greenland grab; pushes Nato for compromise",
      "url": "https://timesofindia.indiatimes.com/world/us/nato-should-be-leading-the-way-donald-trump-renews-push-to-acquire-greenland-citing-security-concerns-links-takeover-to-golden-dome-defence/articleshow/126526475.cms",
      "source": "Times of India",
      "region": "Asia-Pacific",
      "published": "2026-01-14T17:40:36+05:30",
      "sentiment": "positive"
    },
    {
      "title": "Maharashtra civic polls:\u00a0Contest between many avatars of Mahayuti\u00a0and MVA",
      "url": "https://www.thehindu.com/news/national/maharashtra/maharashtra-civic-pollsmahayuti-maha-vikas-agadhi-alliances-contests/article70504699.ece",
      "source": "The Hindu",
      "region": "Asia-Pacific",
      "published": "2026-01-14T17:40:24+05:30",
      "sentiment": "neutral"
    },
    {
      "title": "'Caused severe damage to country': Jamiat chief trains gun at Cong; alleges party enabled hate politics",
      "url": "https://timesofindia.indiatimes.com/india/caused-severe-damage-to-country-jamiat-chief-trains-gun-at-cong-alleges-party-enabled-hate-politics/articleshow/126526192.cms",
      "source": "Times of India",
      "region": "North America",
      "published": "2026-01-14T17:35:45+05:30",
      "sentiment": "negative"
    },
    {
      "title": "SFA recalls Community Co\u2019s diced beetroot product due to potential presence of rust within can",
      "url": "https://www.straitstimes.com/singapore/sfa-recalls-community-cos-diced-beetroot-product-due-to-potential-presence-of-rust-within-can",
      "source": "Straits Times",
      "region": "North America",
      "published": "2026-01-14T17:35:00+08:00",
      "sentiment": "neutral"
    },
    {
      "title": "AI debate: Zoho's Vembu alleges Big Tech dropped climate focus; urges India to lead",
      "url": "https://timesofindia.indiatimes.com/technology/tech-news/zoho-founder-sridhar-vembu-takes-a-dig-at-microsoft-google-amazon-and-others-says-in-the-rush-to-ai-they-have-forgotten-/articleshow/126526340.cms",
      "source": "Times of India",
      "region": "North America",
      "published": "2026-01-14T17:31:47+05:30",
      "sentiment": "neutral"
    },
    {
      "title": "Mamata vs ED: Agency says 'nothing seized'; HC disposes off TMC's plea \u2014 what happened in court",
      "url": "https://timesofindia.indiatimes.com/india/mamata-vs-ed-hc-disposes-off-tmcs-plea-as-agency-says-nothing-seized-what-happened-during-hearing/articleshow/126526349.cms",
      "source": "Times of India",
      "region": "Asia-Pacific",
      "published": "2026-01-14T17:31:27+05:30",
      "sentiment": "neutral"
    },
    {
      "title": "'My conscience remains clear': Workers' Party chief Pritam Singh disagrees his behaviour was dishonourable, unbecoming of an MP",
      "url": "https://www.channelnewsasia.com/singapore/wp-pritam-singh-parliament-leader-opposition-motion-indranee-5855311",
      "source": "Channel News Asia",
      "region": "Global",
      "published": "2026-01-14T17:30:00+08:00",
      "sentiment": "negative"
    },
    {
      "title": "Indranee sets out why Parliament must act \u2018without unnecessary delay\u2019 on Pritam Singh\u2019s conduct",
      "url": "https://www.straitstimes.com/singapore/politics/indranee-sets-out-why-parliament-must-act-without-unnecessary-delay-on-pritam-singhs-conduct",
      "source": "Straits Times",
      "region": "North America",
      "published": "2026-01-14T17:25:07+08:00",
      "sentiment": "positive"
    },
    {
      "title": "Girls in North India told to stay in kitchen, bear children: DMK MP Dayanidhi Maran",
      "url": "https://www.thehindu.com/news/national/tamil-nadu/girls-in-north-india-told-to-stay-in-kitchen-bear-children-dmk-mp-dayanidhi-maran/article70509435.ece",
      "source": "The Hindu",
      "region": "Asia-Pacific",
      "published": "2026-01-14T17:23:26+05:30",
      "sentiment": "neutral"
    },
    {
      "title": "After SC relief to others, another Delhi riots accused files bail plea in city court seeking parity",
      "url": "https://www.thehindu.com/news/cities/Delhi/after-sc-relief-to-others-another-delhi-riots-accused-files-bail-plea-in-city-court-seeking-parity/article70509401.ece",
      "source": "The Hindu",
      "region": "North America",
      "published": "2026-01-14T17:22:05+05:30",
      "sentiment": "negative"
    },
    {
      "title": "Protest erupts against demolition drive at Manikarnika Ghat in Varanasi",
      "url": "https://www.thehindu.com/news/national/uttar-pradesh/protest-erupts-against-demolition-drive-at-manikarnika-ghat-in-varanasi/article70509398.ece",
      "source": "The Hindu",
      "region": "Asia-Pacific",
      "published": "2026-01-14T17:21:43+05:30",
      "sentiment": "negative"
    },
    {
      "title": "Video: 'Anti-Trump' secret agent assigned to Vance caught leaking 'sensitive info'",
      "url": "https://timesofindia.indiatimes.com/world/us/no-tolerance-for-breaches-secret-service-after-anti-trump-agent-assigned-to-jd-vance-caught-on-camera-leaking-sensitive-details/articleshow/126525581.cms",
      "source": "Times of India",
      "region": "North America",
      "published": "2026-01-14T17:20:38+05:30",
      "sentiment": "positive"
    },
    {
      "title": "Inside edge, bowled: Ahmedabad d\u00e9j\u00e0 vu as Kohli's dismissal mirrors 2023 WC final \u2014 Watch",
      "url": "https://timesofindia.indiatimes.com/sports/cricket/india-vs-new-zealand/inside-edge-bowled-ahmedabad-dj-vu-as-virat-kohlis-dismissal-in-second-odi-vs-nz-mirrors-2023-world-cup-final-watch/articleshow/126525084.cms",
      "source": "Times of India",
      "region": "Asia-Pacific",
      "published": "2026-01-14T17:20:29+05:30",
      "sentiment": "negative"
    },
    {
      "title": "Japan yen hits 18-month low; traders weigh up chances of intervention",
      "url": "https://www.channelnewsasia.com/business/japan-yen-hits-18-month-low-traders-weigh-up-chances-intervention-5857141",
      "source": "Channel News Asia",
      "region": "Asia-Pacific",
      "published": "2026-01-14T17:19:54+08:00",
      "sentiment": "negative"
    },
    {
      "title": "Supreme Court to hear on January 15 ED's case for probe into \u2018obstruction\u2019 of I-PAC raids by West Bengal CM",
      "url": "https://www.thehindu.com/news/national/supreme-court-to-hear-on-jan-15-eds-case-for-probe-into-obstruction-of-i-pac-raids-by-west-bengal-cm/article70509309.ece",
      "source": "The Hindu",
      "region": "Asia-Pacific",
      "published": "2026-01-14T17:18:44+05:30",
      "sentiment": "positive"
    },
    {
      "title": "'Under guise of Jihad': Pak exposed again; LeT leader speaks on Kashmir - watch",
      "url": "https://timesofindia.indiatimes.com/world/pakistan/kashmir-issue-can-only-be-resolved-through-jihad-lashkar-leader-issues-threat-video-surfaces/articleshow/126523542.cms",
      "source": "Times of India",
      "region": "Asia-Pacific",
      "published": "2026-01-14T17:18:42+05:30",
      "sentiment": "negative"
    },
    {
      "title": "Fourteen Bills passed by Kerala Assembly awaiting assent, says Speaker A.N. Shamseer",
      "url": "https://www.thehindu.com/news/national/kerala/k/article70509216.ece",
      "source": "The Hindu",
      "region": "Asia-Pacific",
      "published": "2026-01-14T17:16:39+05:30",
      "sentiment": "neutral"
    },
    {
      "title": "Rahul Gandhi \u2018textbook example\u2019 of separatism in Indian politics: BJP",
      "url": "https://www.thehindu.com/news/national/rahul-gandhi-textbook-example-of-separatism-in-indian-politics-bjp/article70509347.ece",
      "source": "The Hindu",
      "region": "Asia-Pacific",
      "published": "2026-01-14T17:09:15+05:30",
      "sentiment": "negative"
    },
    {
      "title": "BJP MLC alleges Karnataka government hiding contents of D\u2019Cunha report on Bengaluru stampede to save face",
      "url": "https://www.thehindu.com/news/national/karnataka/bjp-mlc-alleges-karnataka-government-hiding-contents-of-dcunha-report-on-bengaluru-stampede-to-save-face/article70509158.ece",
      "source": "The Hindu",
      "region": "Asia-Pacific",
      "published": "2026-01-14T17:01:56+05:30",
      "sentiment": "negative"
    },
    {
      "title": "Femella Foundation to stage a play to launch its new initiative against domestic violence",
      "url": "https://www.thehindu.com/society/femella-foundation-to-stage-a-play-to-launch-its-new-initiative-against-domestic-violence/article70504974.ece",
      "source": "The Hindu",
      "region": "Asia-Pacific",
      "published": "2026-01-14T17:00:00+05:30",
      "sentiment": "negative"
    },
    {
      "title": "Stock market holiday: Why BSE and NSE are closed on January 15; what investors should know",
      "url": "https://timesofindia.indiatimes.com/business/india-business/stock-market-holiday-bse-nse-shut-on-january-15-due-to-maharashtra-civic-polls-fo-expiry-preponed/articleshow/126525563.cms",
      "source": "Times of India",
      "region": "Asia-Pacific",
      "published": "2026-01-14T16:56:12+05:30",
      "sentiment": "positive"
    },
    {
      "title": "This Japanese method can grow forests inside cities in just a few years",
      "url": "https://timesofindia.indiatimes.com/science/this-japanese-method-can-grow-forests-inside-cities-in-just-a-few-years/articleshow/126525288.cms",
      "source": "Times of India",
      "region": "Asia-Pacific",
      "published": "2026-01-14T16:52:00+05:30",
      "sentiment": "neutral"
    },
    {
      "title": "\u2018Avoid travelling to Iran\u2019: India issues fresh advisory",
      "url": "https://www.thehindu.com/news/national/centre-issues-advisory-for-citizens-against-travel-to-iran/article70509268.ece",
      "source": "The Hindu",
      "region": "Asia-Pacific",
      "published": "2026-01-14T16:43:07+05:30",
      "sentiment": "positive"
    },
    {
      "title": "Avoid travelling to Iran: India issues fresh advisory",
      "url": "https://www.thehindu.com/news/national/centre-issues-advisory-for-citizens-against-travel-to-iran/article70509268.ece",
      "source": "The Hindu",
      "region": "Asia-Pacific",
      "published": "2026-01-14T16:43:07+05:30",
      "sentiment": "neutral"
    },
    {
      "title": "South Korea vows legal action over drone incursion into North",
      "url": "https://www.channelnewsasia.com/east-asia/south-korea-legal-action-drone-incursion-north-5858186",
      "source": "Channel News Asia",
      "region": "Asia-Pacific",
      "published": "2026-01-14T16:43:00+08:00",
      "sentiment": "positive"
    },
    {
      "title": "T.N. CM Stalin participates in Pongal celebrations at Secretariat",
      "url": "https://www.thehindu.com/news/national/tamil-nadu/tn-cm-stalin-participates-in-pongal-celebrations-at-secretariat/article70509120.ece",
      "source": "The Hindu",
      "region": "Asia-Pacific",
      "published": "2026-01-14T16:42:47+05:30",
      "sentiment": "neutral"
    },
    {
      "title": "'You're exposed': BJP sees red over Assam Cong's now-deleted tweet; what sparked row?",
      "url": "https://timesofindia.indiatimes.com/india/youre-exposed-bjp-sees-red-over-assam-congresss-now-deleted-tweet-what-sparked-row-assam-bjp-hq-fire/articleshow/126524727.cms",
      "source": "Times of India",
      "region": "Asia-Pacific",
      "published": "2026-01-14T16:40:31+05:30",
      "sentiment": "negative"
    },
    {
      "title": "Telangana police detain three NTV journalists over controversial programme",
      "url": "https://www.thehindu.com/news/cities/Hyderabad/telangana-police-detain-three-ntv-journalists-over-controversial-programme/article70509166.ece",
      "source": "The Hindu",
      "region": "Asia-Pacific",
      "published": "2026-01-14T16:38:19+05:30",
      "sentiment": "negative"
    },
    {
      "title": "Bose Krishnamachari resigns from Kochi Biennale Foundation",
      "url": "https://www.thehindu.com/news/national/kerala/bose-krishnamachari-resigns-from-kochi-biennale-foundation/article70509237.ece",
      "source": "The Hindu",
      "region": "North America",
      "published": "2026-01-14T16:38:05+05:30",
      "sentiment": "negative"
    },
    {
      "title": "A lie, its fallout and a motion before Parliament",
      "url": "https://www.straitstimes.com/singapore/politics/a-lie-its-fallout-and-a-motion-before-parliament",
      "source": "Straits Times",
      "region": "Global",
      "published": "2026-01-14T16:35:00+08:00",
      "sentiment": "neutral"
    },
    {
      "title": "Raeesah Khan\u2019s lie, its fallout and a motion against Pritam Singh before Parliament",
      "url": "https://www.straitstimes.com/singapore/politics/a-lie-its-fallout-and-a-motion-before-parliament",
      "source": "Straits Times",
      "region": "North America",
      "published": "2026-01-14T16:35:00+08:00",
      "sentiment": "neutral"
    },
    {
      "title": "Aaron Rodgers takes final dig at Jets in what may be his 2025 farewell",
      "url": "https://timesofindia.indiatimes.com/sports/nfl/news/aaron-rodgers-takes-his-last-2025-season-dig-at-his-former-team-new-york-jets/articleshow/126522477.cms",
      "source": "Times of India",
      "region": "Asia-Pacific",
      "published": "2026-01-14T16:32:00+05:30",
      "sentiment": "positive"
    },
    {
      "title": "'Will boost military presence': Denmark hits back at US' Greenland threat",
      "url": "https://timesofindia.indiatimes.com/world/europe/will-boost-military-presence-denmark-hits-back-at-us-greenland-threat-to-beef-up-arctic-defences/articleshow/126523643.cms",
      "source": "Times of India",
      "region": "North America",
      "published": "2026-01-14T16:31:05+05:30",
      "sentiment": "positive"
    },
    {
      "title": "Pritam has shown failure of leadership, failure to take responsibility: Indranee",
      "url": "https://www.straitstimes.com/singapore/politics/pritam-has-shown-failure-of-leadership-failure-to-take-responsibility-indranee",
      "source": "Straits Times",
      "region": "Global",
      "published": "2026-01-14T16:30:00+08:00",
      "sentiment": "negative"
    },
    {
      "title": "Caregivers of over 14,600 seniors benefited from subsidised respite care services in 2025: MOH",
      "url": "https://www.straitstimes.com/singapore/politics/over-14600-caregivers-of-seniors-benefitted-from-subsidised-respite-care-services-in-2025-moh",
      "source": "Straits Times",
      "region": "Global",
      "published": "2026-01-14T16:30:00+08:00",
      "sentiment": "positive"
    },
    {
      "title": "Cambodia to keep up crackdown on scam centres after arrest of alleged mastermind",
      "url": "https://www.channelnewsasia.com/asia/cambodia-scam-centres-crackdown-chen-zhi-arrest-5857846",
      "source": "Channel News Asia",
      "region": "Global",
      "published": "2026-01-14T16:26:12+08:00",
      "sentiment": "negative"
    },
    {
      "title": "UDF councillors halt railway compound wall work citing obstruction to Kannur road development",
      "url": "https://www.thehindu.com/news/national/kerala/udf-councillors-halt-railway-compound-wall-work-citing-obstruction-to-kannur-road-development/article70509098.ece",
      "source": "The Hindu",
      "region": "Asia-Pacific",
      "published": "2026-01-14T16:25:18+05:30",
      "sentiment": "neutral"
    },
    {
      "title": "Hyderabad Hot Air Balloon festival tickets sell out in minutes; more to be released on January 14",
      "url": "https://www.thehindu.com/news/cities/Hyderabad/hyderabad-hot-air-balloon-festival-tickets-sell-out-in-minutes-more-to-be-released-on-january-14/article70508904.ece",
      "source": "The Hindu",
      "region": "Asia-Pacific",
      "published": "2026-01-14T16:22:50+05:30",
      "sentiment": "positive"
    },
    {
      "title": "LinkedIn founder to Americans: Tariffs are terrible; urges tech CEOs to speak up",
      "url": "https://timesofindia.indiatimes.com/technology/tech-news/linkedin-founder-reid-hoffman-to-americans-tariffs-are-terrible-for-you/articleshow/126524904.cms",
      "source": "Times of India",
      "region": "North America",
      "published": "2026-01-14T16:22:04+05:30",
      "sentiment": "negative"
    },
    {
      "title": "FountainVest secures Italy's nod to buy major stake in EuroGroup Laminations",
      "url": "https://www.channelnewsasia.com/business/fountainvest-secures-italys-nod-buy-major-stake-in-eurogroup-laminations-5858151",
      "source": "Channel News Asia",
      "region": "Europe",
      "published": "2026-01-14T16:20:20+08:00",
      "sentiment": "positive"
    },
    {
      "title": "Indonesia scraps plan to introduce B50 biodiesel this year, will raise palm oil export levy",
      "url": "https://www.channelnewsasia.com/business/indonesia-scraps-plan-introduce-b50-biodiesel-year-will-raise-palm-oil-export-levy-5858141",
      "source": "Channel News Asia",
      "region": "Asia-Pacific",
      "published": "2026-01-14T16:16:54+08:00",
      "sentiment": "neutral"
    },
    {
      "title": "Michael Burry's warning: Investor says Meta's AI bet risks profits; Wall Street stays bullish",
      "url": "https://timesofindia.indiatimes.com/technology/tech-news/one-of-americas-biggest-investors-michael-burry-to-mark-zuckerberg-you-are-making-a-mistake-by-/articleshow/126524743.cms",
      "source": "Times of India",
      "region": "North America",
      "published": "2026-01-14T16:16:40+05:30",
      "sentiment": "positive"
    },
    {
      "title": "Animal welfare laws review will consider requirements for CCTV at pet groomers: Alvin Tan",
      "url": "https://www.straitstimes.com/singapore/politics/animal-welfare-laws-review-will-consider-requirements-for-cctv-at-pet-groomers-alvin-tan",
      "source": "Straits Times",
      "region": "Global",
      "published": "2026-01-14T16:15:00+08:00",
      "sentiment": "negative"
    },
    {
      "title": "MND to consider requiring CCTV at pet grooming businesses in ongoing law review",
      "url": "https://www.channelnewsasia.com/singapore/pet-groomers-animals-and-birds-act-cctv-5857626",
      "source": "Channel News Asia",
      "region": "North America",
      "published": "2026-01-14T16:13:00+08:00",
      "sentiment": "neutral"
    },
    {
      "title": "Toyota Motor group company raises offer for Toyota Industries by 15%",
      "url": "https://www.channelnewsasia.com/business/toyota-motor-group-company-raises-offer-toyota-industries-15-5858131",
      "source": "Channel News Asia",
      "region": "North America",
      "published": "2026-01-14T16:12:50+08:00",
      "sentiment": "neutral"
    },
    {
      "title": "Toyota raises offer for Toyota Industries by 15%",
      "url": "https://www.channelnewsasia.com/business/toyota-raises-offer-toyota-industries-15-5858131",
      "source": "Channel News Asia",
      "region": "North America",
      "published": "2026-01-14T16:12:50+08:00",
      "sentiment": "neutral"
    },
    {
      "title": "Toyota agrees to hike offer for Toyota Industries by 15%",
      "url": "https://www.channelnewsasia.com/business/toyota-agrees-hike-offer-toyota-industries-15-5858131",
      "source": "Channel News Asia",
      "region": "North America",
      "published": "2026-01-14T16:12:50+08:00",
      "sentiment": "positive"
    },
    {
      "title": "$200,000 for palak paneer? Old US campus settlement explodes on social media",
      "url": "https://timesofindia.indiatimes.com/world/us/what-a-joke-200000-palak-paneer-settlement-resurfaces-online-2-indian-phd-students-win-in-food-smell-racist-case/articleshow/126524123.cms",
      "source": "Times of India",
      "region": "Asia-Pacific",
      "published": "2026-01-14T16:10:46+05:30",
      "sentiment": "negative"
    },
    {
      "title": "Parliament motion on Pritam Singh: How the events unfolded",
      "url": "https://www.channelnewsasia.com/singapore/pritam-singh-workers-party-leader-opposition-parliament-motion-5855676",
      "source": "Channel News Asia",
      "region": "Global",
      "published": "2026-01-14T16:03:07+08:00",
      "sentiment": "positive"
    },
    {
      "title": "'Dhurandhar' collection: Film crosses Rs 810 crore; does better than 'The Raja Saab'",
      "url": "https://timesofindia.indiatimes.com/entertainment/hindi/bollywood/box-office/dhurandhar-box-office-collection-day-41-live-the-ranveer-singh-akshaye-khanna-film-slows-down-further-after-crossing-rs-810-crore-does-better-than-prabhas-starrer-new-release-the-raja-saab/articleshow/126524211.cms",
      "source": "Times of India",
      "region": "Asia-Pacific",
      "published": "2026-01-14T16:03:04+05:30",
      "sentiment": "positive"
    },
    {
      "title": "Pritam Singh\u2019s lying \u2018not trivial\u2019, strikes at Singaporeans\u2019 trust in parliament: Leader of the House Indranee Rajah",
      "url": "https://www.channelnewsasia.com/singapore/parliament-indranee-rajah-pritam-singh-leader-opposition-workers-party-mp-motion-5857971",
      "source": "Channel News Asia",
      "region": "Asia-Pacific",
      "published": "2026-01-14T16:03:03+08:00",
      "sentiment": "negative"
    },
    {
      "title": "Aravali degradation: Encroachments, mining &amp; urban sprawl hit ecology - study",
      "url": "https://timesofindia.indiatimes.com/india/aravali-degradation-encroachments-mining-and-urban-sprawl-hit-ecology-study-flags-threat-to-groundwater-biodiversity/articleshow/126523999.cms",
      "source": "Times of India",
      "region": "North America",
      "published": "2026-01-14T16:01:30+05:30",
      "sentiment": "negative"
    },
    {
      "title": "Centre denied political clearance for CM Mann's proposed visit to U.K., Israel: Punjab AAP",
      "url": "https://www.thehindu.com/news/national/punjab/centre-denied-political-clearance-for-cm-manns-proposed-visit-to-uk-israel-punjab-aap/article70509103.ece",
      "source": "The Hindu",
      "region": "Middle East",
      "published": "2026-01-14T16:00:02+05:30",
      "sentiment": "negative"
    },
    {
      "title": "Nestle CEO apologises over instant formula recall",
      "url": "https://www.channelnewsasia.com/world/nestle-ceo-apologises-over-instant-baby-milk-formula-recall-5858046",
      "source": "Channel News Asia",
      "region": "North America",
      "published": "2026-01-14T15:56:00+08:00",
      "sentiment": "negative"
    },
    {
      "title": "Budget 2026: Increased expenditure, clear roadmap &amp; more \u2014 here's what highways need",
      "url": "https://timesofindia.indiatimes.com/business/infrastructure/budget-2026-increased-expenditure-clear-roadmap-more-heres-what-indias-highways-need/articleshow/126523561.cms",
      "source": "Times of India",
      "region": "North America",
      "published": "2026-01-14T15:55:23+05:30",
      "sentiment": "positive"
    },
    {
      "title": "Chinese student numbers at Harvard rise despite Trump visa crackdown",
      "url": "https://www.channelnewsasia.com/world/chinese-student-numbers-rise-harvard-university-united-states-trump-visa-crackdown-5857931",
      "source": "Channel News Asia",
      "region": "Asia-Pacific",
      "published": "2026-01-14T15:52:11+08:00",
      "sentiment": "neutral"
    },
    {
      "title": "Man charged over fatal 2022 Bedok North fire that killed 4 people including 3-year-old girl",
      "url": "https://www.straitstimes.com/singapore/courts-crime/man-charged-over-fatal-2022-bedok-north-fire-that-killed-4-people-including-3-year-old-girl",
      "source": "Straits Times",
      "region": "North America",
      "published": "2026-01-14T15:51:30+08:00",
      "sentiment": "negative"
    },
    {
      "title": "Man charged over  2022 Bedok North fire that killed 4 people including 3-year-old girl",
      "url": "https://www.straitstimes.com/singapore/courts-crime/man-charged-over-fatal-2022-bedok-north-fire-that-killed-4-people-including-3-year-old-girl",
      "source": "Straits Times",
      "region": "North America",
      "published": "2026-01-14T15:51:30+08:00",
      "sentiment": "negative"
    },
    {
      "title": "Man charged over 2022 Bedok North fire that killed 4 people, including 3-year-old girl",
      "url": "https://www.straitstimes.com/singapore/courts-crime/man-charged-over-fatal-2022-bedok-north-fire-that-killed-4-people-including-3-year-old-girl",
      "source": "Straits Times",
      "region": "North America",
      "published": "2026-01-14T15:51:30+08:00",
      "sentiment": "negative"
    },
    {
      "title": "Skanjet Aviation\u2019s initiative to launch regional airline gets backing from Mysore Chamber of Commerce and Industry",
      "url": "https://www.thehindu.com/news/national/karnataka/skanjet-aviations-initiative-to-launch-regional-airline-gets-backing-from-mysore-chamber-of-commerce-and-industry/article70508651.ece",
      "source": "The Hindu",
      "region": "North America",
      "published": "2026-01-14T15:50:40+05:30",
      "sentiment": "positive"
    },
    {
      "title": "'Leave Iran': India's stark advisory amid threat of US attack; protests spread",
      "url": "https://timesofindia.indiatimes.com/india/leave-iran-indias-stark-advisory-amid-threat-of-us-attack-protests-spread/articleshow/126524206.cms",
      "source": "Times of India",
      "region": "Middle East",
      "published": "2026-01-14T15:50:18+05:30",
      "sentiment": "negative"
    },
    {
      "title": "Steam engines behind German wage and innovation gaps 150 years on, study shows",
      "url": "https://www.channelnewsasia.com/business/steam-engines-behind-german-wage-and-innovation-gaps-150-years-study-shows-5858101",
      "source": "Channel News Asia",
      "region": "Global",
      "published": "2026-01-14T15:49:40+08:00",
      "sentiment": "positive"
    },
    {
      "title": "Run machine keeps ticking: Kohli breaks Tendulkar's record; achieves this milestone",
      "url": "https://timesofindia.indiatimes.com/sports/cricket/india-vs-new-zealand/run-machine-keeps-ticking-virat-kohli-breaks-sachin-tendulkars-record-achieves-this-milestone-in-second-odi-vs-nz/articleshow/126523877.cms",
      "source": "Times of India",
      "region": "Asia-Pacific",
      "published": "2026-01-14T15:45:11+05:30",
      "sentiment": "positive"
    },
    {
      "title": "'She was having an affair...': Mary Kom's ex-husband reacts after cheating allegations",
      "url": "https://timesofindia.indiatimes.com/life-style/relationships/family/after-mc-mary-koms-cheating-allegations-her-ex-husband-onler-kom-reacts-and-says-she-was-having-an-affair-/articleshow/126523951.cms",
      "source": "Times of India",
      "region": "North America",
      "published": "2026-01-14T15:40:53+05:30",
      "sentiment": "negative"
    },
    {
      "title": "Over 10,000 jobs to be offered with launch of year-long job fair initiative in East Coast",
      "url": "https://www.straitstimes.com/singapore/community/over-10000-jobs-to-be-offered-with-launch-of-year-long-job-fair-initiative-in-east-coast",
      "source": "Straits Times",
      "region": "Global",
      "published": "2026-01-14T15:35:00+08:00",
      "sentiment": "positive"
    },
    {
      "title": "Bill to formally recognise chess, e-sports and others as sports passed in Parliament",
      "url": "https://www.straitstimes.com/singapore/politics/bill-to-formally-recognise-chess-e-sports-and-others-as-sports-passed-in-parliament",
      "source": "Straits Times",
      "region": "Asia-Pacific",
      "published": "2026-01-14T15:34:10+08:00",
      "sentiment": "positive"
    },
    {
      "title": "\u2018When admitted to the hospital\u2019: Iyer recalls \u2018excruciatingly painful\u2019 injury",
      "url": "https://timesofindia.indiatimes.com/sports/cricket/news/when-i-was-admitted-to-the-hospital-shreyas-iyer-recalls-excruciatingly-painful-injury-shares-recovery-mantra/articleshow/126523714.cms",
      "source": "Times of India",
      "region": "Asia-Pacific",
      "published": "2026-01-14T15:33:48+05:30",
      "sentiment": "negative"
    },
    {
      "title": "Musk warns medical school could be pointless: AI may outperform human doctors",
      "url": "https://timesofindia.indiatimes.com/technology/tech-news/elon-musk-warns-medical-school-could-be-pointless-in-a-future-where-ai-may-outperform-human-doctors-and-revolutionise-healthcare/articleshow/126523725.cms",
      "source": "Times of India",
      "region": "North America",
      "published": "2026-01-14T15:33:28+05:30",
      "sentiment": "negative"
    },
    {
      "title": "Amazon to appeal against Italian fine, even after it was cut, paper says",
      "url": "https://www.channelnewsasia.com/business/amazon-appeal-against-italian-fine-even-after-it-was-cut-paper-says-5858061",
      "source": "Channel News Asia",
      "region": "Global",
      "published": "2026-01-14T15:31:43+08:00",
      "sentiment": "positive"
    },
    {
      "title": "Amazon to appeal against Italian antitrust fine, even after it was cut",
      "url": "https://www.channelnewsasia.com/business/amazon-appeal-against-italian-antitrust-fine-even-after-it-was-cut-5858061",
      "source": "Channel News Asia",
      "region": "North America",
      "published": "2026-01-14T15:31:43+08:00",
      "sentiment": "positive"
    },
    {
      "title": "Mahant Narendra Giri death case: Supreme Court grants bail to accused",
      "url": "https://www.thehindu.com/news/national/mahant-narendra-giri-death-case-supreme-court-grants-bail-to-accused/article70509001.ece",
      "source": "The Hindu",
      "region": "Asia-Pacific",
      "published": "2026-01-14T15:31:25+05:30",
      "sentiment": "negative"
    },
    {
      "title": "'Mamata seized records, committed offence': ED trains guns on CM; I-PAC raid row in HC",
      "url": "https://timesofindia.indiatimes.com/city/kolkata/extraordinary-sign-of-bullying-ed-vs-tmc-in-calcutta-hc-over-i-pac-raids-agency-claims-mamata-banerjee-committed-offence/articleshow/126522766.cms",
      "source": "Times of India",
      "region": "Asia-Pacific",
      "published": "2026-01-14T15:28:03+05:30",
      "sentiment": "negative"
    }
  ]
}